<?xml version="1.0" encoding="utf-8"?>
<install version="1.5" client="both" type="language" method="upgrade">
    <name>French Tienda</name>
    <tag>fr-FR</tag>
    <version>0.7.2 Community</version>
    <creationDate>May 2010</creationDate>
    <author>JC Richard</author>
    <authorEmail>djanubis03@gmail.com</authorEmail>
    <authorUrl>www.lab-project.net</authorUrl>
    <copyright>2012 Dioscouri.com</copyright>
    <copyrightHolder>Dioscouri.com</copyrightHolder>
    <license>GNU General Public License v2</license>
    <description>Pack langue française pour Tienda</description>

	<site>
		<files folder="site">
			<filename>fr-FR.com_tienda.ini</filename>
			<filename>fr-FR.mod_tienda_cart.ini</filename>
			<filename>fr-FR.mod_tienda_categories.ini</filename>
			<filename>fr-FR.mod_tienda_currency.ini</filename>
			<filename>fr-FR.mod_tienda_manufacturers.ini</filename>
			<filename>fr-FR.mod_tienda_my_orderitems.ini</filename>
			<filename>fr-FR.mod_tienda_my_orders.ini</filename>
			<filename>fr-FR.mod_tienda_popular_products.ini</filename>
			<filename>fr-FR.mod_tienda_pricefilters.ini</filename>
			<filename>fr-FR.mod_tienda_products.ini</filename>
			<filename>fr-FR.mod_tienda_quickicon.ini</filename>
			<filename>fr-FR.mod_tienda_recentorders.ini</filename>
			<filename>fr-FR.mod_tienda_salestatistics.ini</filename>
			<filename>fr-FR.mod_tienda_search.ini</filename>
			<filename>fr-FR.mod_tienda_useraddress.ini</filename>
		</files>
	</site>

    <!-- Application/administrator -->
    <administration>
        <files folder="admin">
            <filename>fr-FR.com_tienda.ini</filename>
			<filename>fr-FR.mod_tienda_salestatistics.ini</filename>
			<filename>fr-FR.mod_tienda_useraddress.ini</filename>
			<filename>fr-FR.plg_content_tienda_content_product.ini</filename>
            <filename>fr-FR.plg_search_tienda.ini</filename>
            <filename>fr-FR.plg_system_tienda.ini</filename>
			<filename>fr-FR.plg_system_tienda_subscriptions.ini</filename>
			<filename>fr-FR.plg_system_tienda_zoo.ini</filename>
            <filename>fr-FR.plg_tienda_bug_report.ini</filename>
            <filename>fr-FR.plg_tienda_charts_fusioncharts.ini</filename>
			<filename>fr-FR.plg_tienda_checkoutexample.ini</filename>
            <filename>fr-FR.plg_tienda_payment_2checkout.ini</filename>
			<filename>fr-FR.plg_tienda_payment_authorizedotnet.ini</filename>
			<filename>fr-FR.plg_tienda_payment_googlecheckout.ini</filename>
            <filename>fr-FR.plg_tienda_payment_moneybookers.ini</filename>
            <filename>fr-FR.plg_tienda_payment_offline.ini</filename>
            <filename>fr-FR.plg_tienda_payment_paypal.ini</filename>
			<filename>fr-FR.plg_tienda_payment_paypalpro.ini</filename>
            <filename>fr-FR.plg_tienda_report_bestsellers.ini</filename>
			<filename>fr-FR.plg_tienda_report_cart.ini</filename>
			<filename>fr-FR.plg_tienda_report_lowstock.ini</filename>
			<filename>fr-FR.plg_tienda_report_mostdownloadedfiles.ini</filename>
			<filename>fr-FR.plg_tienda_report_ordered_products.ini</filename>
			<filename>fr-FR.plg_tienda_report_salesbymanufacturer.ini</filename>
			<filename>fr-FR.plg_tienda_report_sales.ini</filename>
			<filename>fr-FR.plg_tienda_report_subscriptions.ini</filename>
			<filename>fr-FR.plg_tienda_shipping_dhl.ini</filename>
            <filename>fr-FR.plg_tienda_shipping_example.ini</filename>
			<filename>fr-FR.plg_tienda_shipping_fedex.ini</filename>
			<filename>fr-FR.plg_tienda_shipping_standard.ini</filename>
			<filename>fr-FR.plg_tienda_shipping_ups.ini</filename>
			<filename>fr-FR.plg_tienda_shipping_usps.ini</filename>
			<filename>fr-FR.plg_tienda_tool_csvimporter.ini</filename>
			<filename>fr-FR.plg_tienda_tool_installsampledata.ini</filename>
            <filename>fr-FR.plg_tienda_tool_virtuemartmigration.ini</filename>
			<filename>fr-FR.plg_tienda_tool_xcartmigration.ini</filename>
        </files>
    </administration>

</install>
