<?xml version="1.0" encoding="utf-8"?>
<install type="module" version="1.5.0" method="upgrade" position="left">
    <name>Product Search</name>
    <author>Dioscouri</author>
    <authorEmail>info@dioscouri.com</authorEmail>
    <authorUrl>http://www.dioscouri.com</authorUrl>
    <version>0.6.1</version>
    <creationDate>August 2010</creationDate>
    <copyright>2010 Dioscouri.com</copyright>
    <license>GNU General Public License</license>
    <description></description>
    <files>
        <filename module="mod_tienda_search">mod_tienda_search.php</filename>
        <filename>index.html</filename>
        <filename>tmpl/default.php</filename>
        <filename>tmpl/index.html</filename>
    </files>
	<languages>
		<language tag="en-GB">languages/en-GB.mod_tienda_search.ini</language>
	</languages>
	<params>
        <param name="filter_text" type="text" default="" label="FILTER TEXT" description="FILTER TEXT DESC" />
		<param name="category_filter" type="list" default="1" label="Display Category Filter" description="">
			<option value="1">ENABLED</option>
			<option value="0">DISABLED</option>
		</param>
        <param name="filter_fields" type="list" default="0" label="FILTER FIELDS" description="FILTER FIELDS DESC">
            <option value="4">NAME ONLY</option>
            <option value="3">NAME_DESCRIPTION</option>
            <option value="2">SKU</option>
            <option value="1">MODEL NUMBER</option>
            <option value="0">All Of The Above</option>
        </param>
		<param name="moduleclass_sfx" type="text" default="" label="Module Class Suffix" description="PARAMMODULECLASSSUFFIX" />
		<param type="spacer" />
    </params>
</install>